qcompute_qnet/__init__.py
qcompute_qnet/core/__init__.py
qcompute_qnet/core/des.py
qcompute_qnet/core/log.py
qcompute_qnet/core/utils.py
qcompute_qnet/devices/__init__.py
qcompute_qnet/devices/beamsplitter.py
qcompute_qnet/devices/channel.py
qcompute_qnet/devices/detector.py
qcompute_qnet/devices/photon.py
qcompute_qnet/devices/random.py
qcompute_qnet/devices/register.py
qcompute_qnet/devices/source.py
qcompute_qnet/functionalities/__init__.py
qcompute_qnet/functionalities/mobility.py
qcompute_qnet/messages/__init__.py
qcompute_qnet/messages/message.py
qcompute_qnet/models/__init__.py
qcompute_qnet/models/bqc/__init__.py
qcompute_qnet/models/bqc/brickwork.py
qcompute_qnet/models/qkd/__init__.py
qcompute_qnet/models/qkd/application.py
qcompute_qnet/models/qkd/error_correction.py
qcompute_qnet/models/qkd/key_generation.py
qcompute_qnet/models/qkd/message.py
qcompute_qnet/models/qkd/node.py
qcompute_qnet/models/qkd/resource_management.py
qcompute_qnet/models/qkd/routing.py
qcompute_qnet/models/qkd/utils.py
qcompute_qnet/models/qpu/__init__.py
qcompute_qnet/models/qpu/env.py
qcompute_qnet/models/qpu/message.py
qcompute_qnet/models/qpu/node.py
qcompute_qnet/models/qpu/protocol.py
qcompute_qnet/protocols/__init__.py
qcompute_qnet/protocols/protocol.py
qcompute_qnet/protocols/resource.py
qcompute_qnet/protocols/routing.py
qcompute_qnet/quantum/__init__.py
qcompute_qnet/quantum/basis.py
qcompute_qnet/quantum/circuit.py
qcompute_qnet/quantum/gate.py
qcompute_qnet/quantum/mcalculus.py
qcompute_qnet/quantum/noise.py
qcompute_qnet/quantum/pattern.py
qcompute_qnet/quantum/state.py
qcompute_qnet/quantum/utils.py
qcompute_qnet/quantum/backends/__init__.py
qcompute_qnet/quantum/backends/mbqc.py
qcompute_qnet/quantum/backends/qcompute.py
qcompute_qnet/topology/__init__.py
qcompute_qnet/topology/link.py
qcompute_qnet/topology/network.py
qcompute_qnet/topology/node.py
qcompute_qnet-1.3.0.dist-info/LICENSE
qcompute_qnet-1.3.0.dist-info/METADATA
qcompute_qnet-1.3.0.dist-info/WHEEL
qcompute_qnet-1.3.0.dist-info/top_level.txt
qcompute_qnet-1.3.0.dist-info/RECORD
