Metadata-Version: 2.1
Name: qcompute-qnet
Version: 1.3.0
Summary: A Quantum NETwork toolkit developed by the Institute for Quantum Computing at Baidu Research.
Home-page: https://quantum-hub.baidu.com/qnet/tutorial-introduction
Author: Institute for Quantum Computing, Baidu INC.
Author-email: quantum@baidu.com
License: Apache 2.0
Classifier: Programming Language :: Python :: 3
Classifier: License :: OSI Approved :: Apache Software License
Classifier: Operating System :: OS Independent
Requires-Python: >=3.8
License-File: LICENSE
Requires-Dist: qcompute (==3.1.0)
Requires-Dist: numpy (>=1.19.3)
Requires-Dist: pandas (>=1.4.2)
Requires-Dist: networkx (>=2.8)
Requires-Dist: matplotlib (>=3.5.1)
